TOPLVL/MAQ_EST.vhd
library ieee;
use ieee.std_logic_1164.all;
use ieee.numeric_std.all;
entity MAQ_EST is
    port(   clk,rst :in std_logic;
            state  :out unsigned(1 downto 0)
    );
end entity;
architecture a_MAQ_EST of MAQ_EST is
        signal estado_s: unsigned(1 downto 0);
        begin
            process(clk,rst)
            begin
                if rst='1' then
                    estado_s <= "00";
                elsif rising_edge(clk) then
                    if estado_s="10" then -- se agora esta em 2
                        estado_s <= "00"; -- o prox vai voltar ao zero
                    else
                        estado_s <= estado_s+1; -- senao avanca
                    end if;
                end if;
            end process;
            state <= estado_s;
end architecture;

TOPLVL/MAQ_EST_tb.vhd
library ieee;
use ieee.std_logic_1164.all;
use ieee.numeric_std.all;

entity MAQ_EST_tb is
end;

architecture a_MAQ_EST_tb of MAQ_EST_tb is
    component MAQ_EST
            port(   clk,rst :in std_logic;
                    state  :out unsigned(1 downto 0)
            );
    end component;
    constant period_time: time := 100 ns;
    signal finished: std_logic :='0';
    signal clk, rst: std_logic;
    signal state: unsigned(1 downto 0);

    begin
        uut: MAQ_EST port map(clk=>clk, rst=>rst, state=>state);
        
        reset_global: process
        begin
            rst<='1';
            wait for period_time*2;
            rst<='0';
            wait;
        end process;

        sim_time_proc: process
        begin  
            wait for 10 us;
            finished<='1';
            wait;
        end process sim_time_proc;
        
        clk_proc: process
        begin
            while finished/='1' loop
                clk <='0';
                wait for period_time/2;
                clk <='1';
                wait for period_time/2;
            end loop;
            wait;
        end process clk_proc;

        process
        begin
                rst <= '1';
                wait for 100 ns;
                rst <= '0';
                wait;
        end process;    
 end architecture a_MAQ_EST_tb;

TOPLVL/maq_est_teste.vcd
$date
  Sun May 14 15:22:13 2023
$end
$version
  GHDL v0
$end
$timescale
  1 fs
$end
$scope module standard $end
$upscope $end
$scope module std_logic_1164 $end
$upscope $end
$scope module numeric_std $end
$upscope $end
$scope module maq_est_tb $end
$var reg 1 ! finished $end
$var reg 1 " clk $end
$var reg 1 # rst $end
$var reg 2 $ state[1:0] $end
$scope module uut $end
$var reg 1 % clk $end
$var reg 1 & rst $end
$var reg 2 ' state[1:0] $end
$var reg 2 ( estado_s[1:0] $end
$upscope $end
$upscope $end
$enddefinitions $end
#0
0!
0"
1#
b00 $
0%
1&
b00 '
b00 (
#50000000
1"
1%
#100000000
0"
X#
0%
X&
#150000000
1"
b01 $
1%
b01 '
b01 (
#200000000
0"
0#
0%
0&
#250000000
1"
b10 $
1%
b10 '
b10 (
#300000000
0"
0%
#350000000
1"
b00 $
1%
b00 '
b00 (
#400000000
0"
0%
#450000000
1"
b01 $
1%
b01 '
b01 (
#500000000
0"
0%
#550000000
1"
b10 $
1%
b10 '
b10 (
#600000000
0"
0%
#650000000
1"
b00 $
1%
b00 '
b00 (
#700000000
0"
0%
#750000000
1"
b01 $
1%
b01 '
b01 (
#800000000
0"
0%
#850000000
1"
b10 $
1%
b10 '
b10 (
#900000000
0"
0%
#950000000
1"
b00 $
1%
b00 '
b00 (
#1000000000
0"
0%
#1050000000
1"
b01 $
1%
b01 '
b01 (
#1100000000
0"
0%
#1150000000
1"
b10 $
1%
b10 '
b10 (
#1200000000
0"
0%
#1250000000
1"
b00 $
1%
b00 '
b00 (
#1300000000
0"
0%
#1350000000
1"
b01 $
1%
b01 '
b01 (
#1400000000
0"
0%
#1450000000
1"
b10 $
1%
b10 '
b10 (
#1500000000
0"
0%
#1550000000
1"
b00 $
1%
b00 '
b00 (
#1600000000
0"
0%
#1650000000
1"
b01 $
1%
b01 '
b01 (
#1700000000
0"
0%
#1750000000
1"
b10 $
1%
b10 '
b10 (
#1800000000
0"
0%
#1850000000
1"
b00 $
1%
b00 '
b00 (
#1900000000
0"
0%
#1950000000
1"
b01 $
1%
b01 '
b01 (
#2000000000
0"
0%
#2050000000
1"
b10 $
1%
b10 '
b10 (
#2100000000
0"
0%
#2150000000
1"
b00 $
1%
b00 '
b00 (
#2200000000
0"
0%
#2250000000
1"
b01 $
1%
b01 '
b01 (
#2300000000
0"
0%
#2350000000
1"
b10 $
1%
b10 '
b10 (
#2400000000
0"
0%
#2450000000
1"
b00 $
1%
b00 '
b00 (
#2500000000
0"
0%
#2550000000
1"
b01 $
1%
b01 '
b01 (
#2600000000
0"
0%
#2650000000
1"
b10 $
1%
b10 '
b10 (
#2700000000
0"
0%
#2750000000
1"
b00 $
1%
b00 '
b00 (
#2800000000
0"
0%
#2850000000
1"
b01 $
1%
b01 '
b01 (
#2900000000
0"
0%
#2950000000
1"
b10 $
1%
b10 '
b10 (
#3000000000
0"
0%
#3050000000
1"
b00 $
1%
b00 '
b00 (
#3100000000
0"
0%
#3150000000
1"
b01 $
1%
b01 '
b01 (
#3200000000
0"
0%
#3250000000
1"
b10 $
1%
b10 '
b10 (
#3300000000
0"
0%
#3350000000
1"
b00 $
1%
b00 '
b00 (
#3400000000
0"
0%
#3450000000
1"
b01 $
1%
b01 '
b01 (
#3500000000
0"
0%
#3550000000
1"
b10 $
1%
b10 '
b10 (
#3600000000
0"
0%
#3650000000
1"
b00 $
1%
b00 '
b00 (
#3700000000
0"
0%
#3750000000
1"
b01 $
1%
b01 '
b01 (
#3800000000
0"
0%
#3850000000
1"
b10 $
1%
b10 '
b10 (
#3900000000
0"
0%
#3950000000
1"
b00 $
1%
b00 '
b00 (
#4000000000
0"
0%
#4050000000
1"
b01 $
1%
b01 '
b01 (
#4100000000
0"
0%
#4150000000
1"
b10 $
1%
b10 '
b10 (
#4200000000
0"
0%
#4250000000
1"
b00 $
1%
b00 '
b00 (
#4300000000
0"
0%
#4350000000
1"
b01 $
1%
b01 '
b01 (
#4400000000
0"
0%
#4450000000
1"
b10 $
1%
b10 '
b10 (
#4500000000
0"
0%
#4550000000
1"
b00 $
1%
b00 '
b00 (
#4600000000
0"
0%
#4650000000
1"
b01 $
1%
b01 '
b01 (
#4700000000
0"
0%
#4750000000
1"
b10 $
1%
b10 '
b10 (
#4800000000
0"
0%
#4850000000
1"
b00 $
1%
b00 '
b00 (
#4900000000
0"
0%
#4950000000
1"
b01 $
1%
b01 '
b01 (
#5000000000
0"
0%
#5050000000
1"
b10 $
1%
b10 '
b10 (
#5100000000
0"
0%
#5150000000
1"
b00 $
1%
b00 '
b00 (
#5200000000
0"
0%
#5250000000
1"
b01 $
1%
b01 '
b01 (
#5300000000
0"
0%
#5350000000
1"
b10 $
1%
b10 '
b10 (
#5400000000
0"
0%
#5450000000
1"
b00 $
1%
b00 '
b00 (
#5500000000
0"
0%
#5550000000
1"
b01 $
1%
b01 '
b01 (
#5600000000
0"
0%
#5650000000
1"
b10 $
1%
b10 '
b10 (
#5700000000
0"
0%
#5750000000
1"
b00 $
1%
b00 '
b00 (
#5800000000
0"
0%
#5850000000
1"
b01 $
1%
b01 '
b01 (
#5900000000
0"
0%
#5950000000
1"
b10 $
1%
b10 '
b10 (
#6000000000
0"
0%
#6050000000
1"
b00 $
1%
b00 '
b00 (
#6100000000
0"
0%
#6150000000
1"
b01 $
1%
b01 '
b01 (
#6200000000
0"
0%
#6250000000
1"
b10 $
1%
b10 '
b10 (
#6300000000
0"
0%
#6350000000
1"
b00 $
1%
b00 '
b00 (
#6400000000
0"
0%
#6450000000
1"
b01 $
1%
b01 '
b01 (
#6500000000
0"
0%
#6550000000
1"
b10 $
1%
b10 '
b10 (
#6600000000
0"
0%
#6650000000
1"
b00 $
1%
b00 '
b00 (
#6700000000
0"
0%
#6750000000
1"
b01 $
1%
b01 '
b01 (
#6800000000
0"
0%
#6850000000
1"
b10 $
1%
b10 '
b10 (
#6900000000
0"
0%
#6950000000
1"
b00 $
1%
b00 '
b00 (
#7000000000
0"
0%
#7050000000
1"
b01 $
1%
b01 '
b01 (
#7100000000
0"
0%
#7150000000
1"
b10 $
1%
b10 '
b10 (
#7200000000
0"
0%
#7250000000
1"
b00 $
1%
b00 '
b00 (
#7300000000
0"
0%
#7350000000
1"
b01 $
1%
b01 '
b01 (
#7400000000
0"
0%
#7450000000
1"
b10 $
1%
b10 '
b10 (
#7500000000
0"
0%
#7550000000
1"
b00 $
1%
b00 '
b00 (
#7600000000
0"
0%
#7650000000
1"
b01 $
1%
b01 '
b01 (
#7700000000
0"
0%
#7750000000
1"
b10 $
1%
b10 '
b10 (
#7800000000
0"
0%
#7850000000
1"
b00 $
1%
b00 '
b00 (
#7900000000
0"
0%
#7950000000
1"
b01 $
1%
b01 '
b01 (
#8000000000
0"
0%
#8050000000
1"
b10 $
1%
b10 '
b10 (
#8100000000
0"
0%
#8150000000
1"
b00 $
1%
b00 '
b00 (
#8200000000
0"
0%
#8250000000
1"
b01 $
1%
b01 '
b01 (
#8300000000
0"
0%
#8350000000
1"
b10 $
1%
b10 '
b10 (
#8400000000
0"
0%
#8450000000
1"
b00 $
1%
b00 '
b00 (
#8500000000
0"
0%
#8550000000
1"
b01 $
1%
b01 '
b01 (
#8600000000
0"
0%
#8650000000
1"
b10 $
1%
b10 '
b10 (
#8700000000
0"
0%
#8750000000
1"
b00 $
1%
b00 '
b00 (
#8800000000
0"
0%
#8850000000
1"
b01 $
1%
b01 '
b01 (
#8900000000
0"
0%
#8950000000
1"
b10 $
1%
b10 '
b10 (
#9000000000
0"
0%
#9050000000
1"
b00 $
1%
b00 '
b00 (
#9100000000
0"
0%
#9150000000
1"
b01 $
1%
b01 '
b01 (
#9200000000
0"
0%
#9250000000
1"
b10 $
1%
b10 '
b10 (
#9300000000
0"
0%
#9350000000
1"
b00 $
1%
b00 '
b00 (
#9400000000
0"
0%
#9450000000
1"
b01 $
1%
b01 '
b01 (
#9500000000
0"
0%
#9550000000
1"
b10 $
1%
b10 '
b10 (
#9600000000
0"
0%
#9650000000
1"
b00 $
1%
b00 '
b00 (
#9700000000
0"
0%
#9750000000
1"
b01 $
1%
b01 '
b01 (
#9800000000
0"
0%
#9850000000
1"
b10 $
1%
b10 '
b10 (
#9900000000
0"
0%
#9950000000
1"
b00 $
1%
b00 '
b00 (
#10000000000
1!
0"
0%
#10050000000
1"
b01 $
1%
b01 '
b01 (
