mux2x1.vhd
library ieee;
use ieee.std_logic_1164.all;
use ieee.numeric_std.all;

entity mux2x1 is
    port( sinal1: in unsigned(15 downto 0);
          sinal2: in unsigned(15 downto 0);
		  sel:  in unsigned;
          saida: out unsigned(15 downto 0)
		);
end entity;


architecture a_mux2x1 of mux2x1 is
begin
    saida <= sinal1 when sel="0" else
             sinal2 when sel="1" else
            "0000000000000000";
end architecture;

BANCOREG/REGISTRADOR.vhd
library ieee;
use ieee.std_logic_1164.all;
use ieee.numeric_std.all;

entity REGISTRADOR is
    port( clk       :in std_logic;
          rst       :in std_logic;
          wr_en     :in std_logic;
          data_in   :in unsigned(15 downto 0);
          data_out  :out unsigned(15 downto 0)
    );
end entity;

architecture a_REGISTRADOR of REGISTRADOR is
    signal registro: unsigned(15 downto 0);
begin
    process(clk, rst, wr_en)
    begin
        if rst='1' then
            registro <="0000000000000000";
        elsif wr_en='1' then
            if rising_edge(clk) then
                registro<=data_in;
            end if;
        end if;
    end process;

        data_out <= registro;
end architecture;

BANCOREG/BANCOREG.vhd
library ieee;
use ieee.std_logic_1164.all;
use ieee.numeric_std.all;

entity BANCOREG is
    port(
        reg1: in unsigned(2 downto 0);
        reg2: in unsigned(2 downto 0);
        dado: in unsigned(15 downto 0);
        wr_reg: in unsigned(2 downto 0);
        wr_en: in std_logic;
        clk: in std_logic;
        rst: in std_logic;
        read_data1: out unsigned(15 downto 0);
        read_data2: out unsigned(15 downto 0)
    );
end entity;
architecture a_BANCOREG of BANCOREG is
    component REGISTRADOR is
        port(
            clk       :in std_logic;
            rst       :in std_logic;
            wr_en     :in std_logic;
            data_in   :in unsigned(15 downto 0);
            data_out  :out unsigned(15 downto 0)
      );
    end component;

    signal r_data0, r_data1, r_data2, r_data3, r_data4, r_data5, r_data6, r_data7: unsigned(15 downto 0);
    signal wr_en0, wr_en1, wr_en2, wr_en3, wr_en4, wr_en5, wr_en6, wr_en7: std_logic;
        begin
        REGISTRADOR0: REGISTRADOR port map(clk=> clk, rst=>rst, wr_en=>wr_en0, data_in=>dado, data_out=>r_data0);
        REGISTRADOR1: REGISTRADOR port map(clk=> clk, rst=>rst, wr_en=>wr_en1, data_in=>dado, data_out=>r_data1);
        REGISTRADOR2: REGISTRADOR port map(clk=> clk, rst=>rst, wr_en=>wr_en2, data_in=>dado, data_out=>r_data2);
        REGISTRADOR3: REGISTRADOR port map(clk=> clk, rst=>rst, wr_en=>wr_en3, data_in=>dado, data_out=>r_data3);
        REGISTRADOR4: REGISTRADOR port map(clk=> clk, rst=>rst, wr_en=>wr_en4, data_in=>dado, data_out=>r_data4);
        REGISTRADOR5: REGISTRADOR port map(clk=> clk, rst=>rst, wr_en=>wr_en5, data_in=>dado, data_out=>r_data5);
        REGISTRADOR6: REGISTRADOR port map(clk=> clk, rst=>rst, wr_en=>wr_en6, data_in=>dado, data_out=>r_data6);
        REGISTRADOR7: REGISTRADOR port map(clk=> clk, rst=>rst, wr_en=>wr_en7, data_in=>dado, data_out=>r_data7);
        
        read_data1 <= r_data0 when reg1 = "000" else
                      r_data1 when reg1 ="001" else
                      r_data2 when reg1 = "010" else
                      r_data3 when reg1 = "011" else
                      r_data4 when reg1 ="100" else
                      r_data5 when reg1 = "101" else
                      r_data6 when reg1 = "110" else
                      r_data7 when reg1 ="111" else
                      "0000000000000000";

        read_data2 <= r_data0 when reg2 = "000" else
                      r_data1 when reg2 ="001" else
                      r_data2 when reg2 = "010" else
                      r_data3 when reg2 = "011" else
                      r_data4 when reg2 ="100" else
                      r_data5 when reg2 = "101" else
                      r_data6 when reg2 = "110" else
                      r_data7 when reg2 ="111" else
                      "0000000000000000";
        
        wr_en0 <= wr_en when wr_reg ="000" else '0';
        wr_en1 <= wr_en when wr_reg ="001" else '0';
        wr_en2 <= wr_en when wr_reg ="010" else '0';
        wr_en3 <= wr_en when wr_reg ="011" else '0';
        wr_en4 <= wr_en when wr_reg ="100" else '0';
        wr_en5 <= wr_en when wr_reg ="101" else '0';
        wr_en6 <= wr_en when wr_reg ="110" else '0';
        wr_en7 <= wr_en when wr_reg ="111" else '0';

    end architecture;

BANCOREG+ULA/operacoes.vhd
library ieee;
use ieee.std_logic_1164.all;
use ieee.numeric_std.all;

entity operacoes is
    port( val0: in unsigned(15 downto 0);
          val1: in unsigned(15 downto 0);
          soma: out unsigned(15 downto 0);
          subtracao: out unsigned(15 downto 0); 
          maior_que : out unsigned(15 downto 0);
          multiplicacao: out unsigned(15 downto 0));

end entity;


architecture a_operacoes of operacoes is
signal soma_ext: unsigned (16 downto 0);
signal multip_ext: unsigned (31 downto 0);
begin
	soma_ext <= ('0' & val0) + val1;
    soma <= soma_ext(15 downto 0);
    subtracao <= val0-val1;
    maior_que<= "0000000000000001" when val0>val1 else
                "0000000000000000" when val0<=val1 else
                "0000000000000000" ;
	multip_ext <= val0 * val1;
    multiplicacao <= multip_ext (15 downto 0); 
end architecture;

TOPLVL/MUX4x1.vhd
library ieee;
use ieee.std_logic_1164.all;
use ieee.numeric_std.all;

entity MUX4x1 is
    port( ope1: in unsigned(15 downto 0);
          ope2: in unsigned(15 downto 0);
          ope3: in unsigned(15 downto 0);
          ope4: in unsigned(15 downto 0); 
          sel : in unsigned(1 downto 0);
          saida: out unsigned(15 downto 0));
end entity;


architecture a_MUX4x1 of MUX4x1 is
begin
    saida <= ope1 when sel="00" else
             ope2 when sel="01" else
             ope3 when sel="10" else
             ope4 when sel="11" else
            "0000000000000000";
end architecture;

ULA/ULA.vhd
library ieee;
use ieee.std_logic_1164.all;
use ieee.numeric_std.all;

entity ULA is
    port(
            val0: in unsigned(15 downto 0);
            val1: in unsigned(15 downto 0);
            sel: in unsigned(1 downto 0);
            saida: out unsigned(15 downto 0)

    );
end entity;

architecture a_ULA of ULA is
    component mux4x1 is
        port( ope1: in unsigned(15 downto 0);
          ope2: in unsigned(15 downto 0);
          ope3: in unsigned(15 downto 0);
          ope4: in unsigned(15 downto 0); 
          sel : in unsigned(1 downto 0);
          saida: out unsigned(15 downto 0));
    end component;
    component operacoes is
        port( val0: in unsigned(15 downto 0);
        val1: in unsigned(15 downto 0);
        soma: out unsigned(15 downto 0);
        subtracao: out unsigned(15 downto 0); 
        maior_que : out unsigned(15 downto 0);
        multiplicacao: out unsigned(15 downto 0));
    end component;
    signal ope1, ope2, ope3, ope4: unsigned(15 downto 0);
        begin 
            mux4x11: mux4x1 port map (saida=>saida, ope1=>ope1, ope2=>ope2, ope3=>ope3,ope4=>ope4, sel=>sel);
            operacoes1: operacoes port map (val0=>val0, val1=>val1, soma=>ope1, subtracao=>ope2, maior_que=>ope3, multiplicacao=>ope4);
end architecture;

BANCOREG+ULA/TOPLVL.vhd
library ieee;
use ieee.std_logic_1164.all;
use ieee.numeric_std.all;

entity TOPLVL is
	port(
        mux_sel: in unsigned (0 downto 0);
		banco_r1: in unsigned (2 downto 0);
		banco_r2: in unsigned (2 downto 0);
		write_reg: in unsigned (2 downto 0);
		clock: in std_logic;
		reset: in std_logic;
		write_en: in std_logic;
		ula_result: out unsigned (15 downto 0);
		ula_sel: in unsigned (1 downto 0);
		mux_s2: in unsigned (15 downto 0)
    );
end entity;

architecture a_TOPLVL of TOPLVL is
	component BANCOREG is
		port(
			reg1: in unsigned(2 downto 0);
			reg2: in unsigned(2 downto 0);
			dado: in unsigned(15 downto 0);
			wr_reg: in unsigned(2 downto 0);
			wr_en: in std_logic;
			clk: in std_logic;
			rst: in std_logic;
			read_data1: out unsigned(15 downto 0);
			read_data2: out unsigned(15 downto 0)
		);
	end component;
	
	component ULA is
		port(
            val0: in unsigned(15 downto 0);
            val1: in unsigned(15 downto 0);
            sel: in unsigned(1 downto 0);
            saida: out unsigned(15 downto 0)
		);
	end component;
	
	component mux2x1 is
		port( sinal1: in unsigned(15 downto 0);
			sinal2: in unsigned(15 downto 0);
			sel:	  in unsigned;
			saida: out unsigned(15 downto 0)
			);
	end component;
	
	signal ula_out, read_d1, read_d2, mux_out: unsigned (15 downto 0);
	
	begin
		ULA0: ULA port map (val0 => read_d1, val1=> mux_out, sel => ula_sel, saida=> ula_out);
		BANCOREG0: BANCOREG port map (reg1=> banco_r1, reg2=> banco_r2, dado=> ula_out, wr_reg=> write_reg, wr_en=> write_en, clk=> clock, rst=> reset, read_data1=> read_d1, read_data2=> read_d2);
		MUX0: mux2x1 port map (sinal1=> read_d2, sinal2=> mux_s2, sel=> mux_sel, saida=> mux_out);
		ula_result<=ula_out;
end architecture;

BANCOREG+ULA/TOPLVL_tb.vhd
library ieee;
use ieee.std_logic_1164.all;
use ieee.numeric_std.all;

entity TOPLVL_tb is
end;

architecture a_TOPLVL_tb of TOPLVL_tb is
    component TOPLVL is
        port(
            mux_sel: in unsigned (0 downto 0);
			banco_r1: in unsigned (2 downto 0);
			banco_r2: in unsigned (2 downto 0);
			write_reg: in unsigned (2 downto 0);
			clock: in std_logic;
			reset: in std_logic;
			write_en: in std_logic;
			ula_result: out unsigned (15 downto 0);
			ula_sel: in unsigned (1 downto 0);
			mux_s2: in unsigned (15 downto 0)
        );
    end component;
    constant period_time: time := 100 ns;
    signal finished: std_logic :='0';
    signal clk, rst, wr_en: std_logic;
    signal ula_result, mux_s2:unsigned (15 downto 0);
    signal reg1, reg2, wr_reg: unsigned  (2 downto 0);
	signal mux_sel: unsigned (0 downto 0);
	signal ula_sel: unsigned (1 downto 0);

        begin
            uut: TOPLVL port map(mux_sel=> mux_sel, banco_r1=> reg1, banco_r2=> reg2, write_reg=> wr_reg,
			clock=> clk, reset=> rst, write_en=> wr_en, ula_result=> ula_result, ula_sel=> ula_sel, mux_s2=> mux_s2);

        reset_global: process
        begin
            rst<='1';
            wait for period_time*2;
            rst<='0';
            wait;
        end process;

        sim_time_proc: process
        begin  
            wait for 10 us;
            finished<='1';
            wait;
        end process sim_time_proc;
        
        clk_proc: process
        begin
            while finished/='1' loop
                clk <='0';
                wait for period_time/2;
                clk <='1';
                wait for period_time/2;
            end loop;
            wait;
        end process clk_proc;

        process
        begin  
                wait for 200 ns;
                wr_reg<="001";
                wr_en<='1';
                reg1<="000";
                reg2<="001";
				mux_sel<="1";
				ula_sel<="00";
                mux_s2<="0000000000111111";

                wait for 100 ns;
                wr_reg<="000";
                wr_en<='1';
                reg1<="001";
                reg2<="000";
				mux_sel<="1";
				ula_sel<="00";
                mux_s2<="0000000011110000";
				
				wait for 100 ns;
                wr_reg<="010";
                wr_en<='1';
                reg1<="001";
                reg2<="000";
				mux_sel<="0";
				ula_sel<="00";
                mux_s2<="0000000011110000";
				
				wait for 100 ns;
                wr_reg<="000";
                wr_en<='0';
                reg1<="011";
                reg2<="010";
				mux_sel<="0";
				ula_sel<="00";
                mux_s2<="0000000011110000";
                wait;
        end process;
end architecture a_TOPLVL_tb;

BANCOREG+ULA/TOPLVL.vcd
$date
  Wed Apr 19 12:01:54 2023
$end
$version
  GHDL v0
$end
$timescale
  1 fs
$end
$scope module standard $end
$upscope $end
$scope module std_logic_1164 $end
$upscope $end
$scope module numeric_std $end
$upscope $end
$scope module toplvl_tb $end
$var reg 1 ! finished $end
$var reg 1 " clk $end
$var reg 1 # rst $end
$var reg 1 $ wr_en $end
$var reg 16 % ula_result[15:0] $end
$var reg 16 & mux_s2[15:0] $end
$var reg 3 ' reg1[2:0] $end
$var reg 3 ( reg2[2:0] $end
$var reg 3 ) wr_reg[2:0] $end
$var reg 1 * mux_sel[0:0] $end
$var reg 2 + ula_sel[1:0] $end
$scope module uut $end
$var reg 1 , mux_sel[0:0] $end
$var reg 3 - banco_r1[2:0] $end
$var reg 3 . banco_r2[2:0] $end
$var reg 3 / write_reg[2:0] $end
$var reg 1 0 clock $end
$var reg 1 1 reset $end
$var reg 1 2 write_en $end
$var reg 16 3 ula_result[15:0] $end
$var reg 2 4 ula_sel[1:0] $end
$var reg 16 5 mux_s2[15:0] $end
$var reg 16 6 ula_out[15:0] $end
$var reg 16 7 read_d1[15:0] $end
$var reg 16 8 read_d2[15:0] $end
$var reg 16 9 mux_out[15:0] $end
$scope module ula0 $end
$var reg 16 : val0[15:0] $end
$var reg 16 ; val1[15:0] $end
$var reg 2 < sel[1:0] $end
$var reg 16 = saida[15:0] $end
$var reg 16 > ope1[15:0] $end
$var reg 16 ? ope2[15:0] $end
$var reg 16 @ ope3[15:0] $end
$var reg 16 A ope4[15:0] $end
$scope module mux4x11 $end
$var reg 16 B ope1[15:0] $end
$var reg 16 C ope2[15:0] $end
$var reg 16 D ope3[15:0] $end
$var reg 16 E ope4[15:0] $end
$var reg 2 F sel[1:0] $end
$var reg 16 G saida[15:0] $end
$upscope $end
$scope module operacoes1 $end
$var reg 16 H val0[15:0] $end
$var reg 16 I val1[15:0] $end
$var reg 16 J soma[15:0] $end
$var reg 16 K subtracao[15:0] $end
$var reg 16 L maior_que[15:0] $end
$var reg 16 M multiplicacao[15:0] $end
$var reg 17 N soma_ext[16:0] $end
$var reg 32 O multip_ext[31:0] $end
$upscope $end
$upscope $end
$scope module bancoreg0 $end
$var reg 3 P reg1[2:0] $end
$var reg 3 Q reg2[2:0] $end
$var reg 16 R dado[15:0] $end
$var reg 3 S wr_reg[2:0] $end
$var reg 1 T wr_en $end
$var reg 1 U clk $end
$var reg 1 V rst $end
$var reg 16 W read_data1[15:0] $end
$var reg 16 X read_data2[15:0] $end
$var reg 16 Y r_data0[15:0] $end
$var reg 16 Z r_data1[15:0] $end
$var reg 16 [ r_data2[15:0] $end
$var reg 16 \ r_data3[15:0] $end
$var reg 16 ] r_data4[15:0] $end
$var reg 16 ^ r_data5[15:0] $end
$var reg 16 _ r_data6[15:0] $end
$var reg 16 ` r_data7[15:0] $end
$var reg 1 a wr_en0 $end
$var reg 1 b wr_en1 $end
$var reg 1 c wr_en2 $end
$var reg 1 d wr_en3 $end
$var reg 1 e wr_en4 $end
$var reg 1 f wr_en5 $end
$var reg 1 g wr_en6 $end
$var reg 1 h wr_en7 $end
$scope module registrador0 $end
$var reg 1 i clk $end
$var reg 1 j rst $end
$var reg 1 k wr_en $end
$var reg 16 l data_in[15:0] $end
$var reg 16 m data_out[15:0] $end
$var reg 16 n registro[15:0] $end
$upscope $end
$scope module registrador1 $end
$var reg 1 o clk $end
$var reg 1 p rst $end
$var reg 1 q wr_en $end
$var reg 16 r data_in[15:0] $end
$var reg 16 s data_out[15:0] $end
$var reg 16 t registro[15:0] $end
$upscope $end
$scope module registrador2 $end
$var reg 1 u clk $end
$var reg 1 v rst $end
$var reg 1 w wr_en $end
$var reg 16 x data_in[15:0] $end
$var reg 16 y data_out[15:0] $end
$var reg 16 z registro[15:0] $end
$upscope $end
$scope module registrador3 $end
$var reg 1 { clk $end
$var reg 1 | rst $end
$var reg 1 } wr_en $end
$var reg 16 !" data_in[15:0] $end
$var reg 16 "" data_out[15:0] $end
$var reg 16 #" registro[15:0] $end
$upscope $end
$scope module registrador4 $end
$var reg 1 $" clk $end
$var reg 1 %" rst $end
$var reg 1 &" wr_en $end
$var reg 16 '" data_in[15:0] $end
$var reg 16 (" data_out[15:0] $end
$var reg 16 )" registro[15:0] $end
$upscope $end
$scope module registrador5 $end
$var reg 1 *" clk $end
$var reg 1 +" rst $end
$var reg 1 ," wr_en $end
$var reg 16 -" data_in[15:0] $end
$var reg 16 ." data_out[15:0] $end
$var reg 16 /" registro[15:0] $end
$upscope $end
$scope module registrador6 $end
$var reg 1 0" clk $end
$var reg 1 1" rst $end
$var reg 1 2" wr_en $end
$var reg 16 3" data_in[15:0] $end
$var reg 16 4" data_out[15:0] $end
$var reg 16 5" registro[15:0] $end
$upscope $end
$scope module registrador7 $end
$var reg 1 6" clk $end
$var reg 1 7" rst $end
$var reg 1 8" wr_en $end
$var reg 16 9" data_in[15:0] $end
$var reg 16 :" data_out[15:0] $end
$var reg 16 ;" registro[15:0] $end
$upscope $end
$upscope $end
$scope module mux0 $end
$var reg 16 <" sinal1[15:0] $end
$var reg 16 =" sinal2[15:0] $end
$var reg 1 >" sel[0:0] $end
$var reg 16 ?" saida[15:0] $end
$upscope $end
$upscope $end
$upscope $end
$enddefinitions $end
#0
0!
0"
1#
U$
b0000000000000000 %
bUUUUUUUUUUUUUUUU &
bUUU '
bUUU (
bUUU )
bU *
bUU +
bU ,
bUUU -
bUUU .
bUUU /
00
11
U2
b0000000000000000 3
bUU 4
bUUUUUUUUUUUUUUUU 5
b0000000000000000 6
b0000000000000000 7
b0000000000000000 8
b0000000000000000 9
b0000000000000000 :
b0000000000000000 ;
bUU <
b0000000000000000 =
b0000000000000000 >
b0000000000000000 ?
b0000000000000000 @
b0000000000000000 A
b0000000000000000 B
b0000000000000000 C
b0000000000000000 D
b0000000000000000 E
bUU F
b0000000000000000 G
b0000000000000000 H
b0000000000000000 I
b0000000000000000 J
b0000000000000000 K
b0000000000000000 L
b0000000000000000 M
b00000000000000000 N
b00000000000000000000000000000000 O
bUUU P
bUUU Q
b0000000000000000 R
bUUU S
UT
0U
1V
b0000000000000000 W
b0000000000000000 X
b0000000000000000 Y
b0000000000000000 Z
b0000000000000000 [
b0000000000000000 \
b0000000000000000 ]
b0000000000000000 ^
b0000000000000000 _
b0000000000000000 `
0a
0b
0c
0d
0e
0f
0g
0h
0i
1j
0k
b0000000000000000 l
b0000000000000000 m
b0000000000000000 n
0o
1p
0q
b0000000000000000 r
b0000000000000000 s
b0000000000000000 t
0u
1v
0w
b0000000000000000 x
b0000000000000000 y
b0000000000000000 z
0{
1|
0}
b0000000000000000 !"
b0000000000000000 ""
b0000000000000000 #"
0$"
1%"
0&"
b0000000000000000 '"
b0000000000000000 ("
b0000000000000000 )"
0*"
1+"
0,"
b0000000000000000 -"
b0000000000000000 ."
b0000000000000000 /"
00"
11"
02"
b0000000000000000 3"
b0000000000000000 4"
b0000000000000000 5"
06"
17"
08"
b0000000000000000 9"
b0000000000000000 :"
b0000000000000000 ;"
b0000000000000000 <"
bUUUUUUUUUUUUUUUU ="
bU >"
b0000000000000000 ?"
#50000000
1"
10
1U
1i
1o
1u
1{
1$"
1*"
10"
16"
#100000000
0"
00
0U
0i
0o
0u
0{
0$"
0*"
00"
06"
#150000000
1"
10
1U
1i
1o
1u
1{
1$"
1*"
10"
16"
#200000000
0"
0#
1$
b0000000000111111 %
b0000000000111111 &
b000 '
b001 (
b001 )
b1 *
b00 +
b1 ,
b000 -
b001 .
b001 /
00
01
12
b0000000000111111 3
b00 4
b0000000000111111 5
b0000000000111111 6
b0000000000111111 9
b0000000000111111 ;
b00 <
b0000000000111111 =
b0000000000111111 >
b1111111111000001 ?
b0000000000111111 B
b1111111111000001 C
b00 F
b0000000000111111 G
b0000000000111111 I
b0000000000111111 J
b1111111111000001 K
b00000000000111111 N
b000 P
b001 Q
b0000000000111111 R
b001 S
1T
0U
0V
1b
0i
0j
b0000000000111111 l
0o
0p
1q
b0000000000111111 r
0u
0v
b0000000000111111 x
0{
0|
b0000000000111111 !"
0$"
0%"
b0000000000111111 '"
0*"
0+"
b0000000000111111 -"
00"
01"
b0000000000111111 3"
06"
07"
b0000000000111111 9"
b0000000000111111 ="
b1 >"
b0000000000111111 ?"
#250000000
1"
10
b0000000000111111 8
1U
b0000000000111111 X
b0000000000111111 Z
1i
1o
b0000000000111111 s
b0000000000111111 t
1u
1{
1$"
1*"
10"
16"
b0000000000111111 <"
#300000000
0"
b0000000100101111 %
b0000000011110000 &
b001 '
b000 (
b000 )
b001 -
b000 .
b000 /
00
b0000000100101111 3
b0000000011110000 5
b0000000100101111 6
b0000000000111111 7
b0000000000000000 8
b0000000011110000 9
b0000000000111111 :
b0000000011110000 ;
b0000000100101111 =
b0000000100101111 >
b1111111101001111 ?
b0011101100010000 A
b0000000100101111 B
b1111111101001111 C
b0011101100010000 E
b0000000100101111 G
b0000000000111111 H
b0000000011110000 I
b0000000100101111 J
b1111111101001111 K
b0011101100010000 M
b00000000100101111 N
b00000000000000000011101100010000 O
b001 P
b000 Q
b0000000100101111 R
b000 S
0U
b0000000000111111 W
b0000000000000000 X
1a
0b
0i
1k
b0000000100101111 l
0o
0q
b0000000100101111 r
0u
b0000000100101111 x
0{
b0000000100101111 !"
0$"
b0000000100101111 '"
0*"
b0000000100101111 -"
00"
b0000000100101111 3"
06"
b0000000100101111 9"
b0000000000000000 <"
b0000000011110000 ="
b0000000011110000 ?"
#350000000
1"
10
b0000000100101111 8
1U
b0000000100101111 X
b0000000100101111 Y
1i
b0000000100101111 m
b0000000100101111 n
1o
1u
1{
1$"
1*"
10"
16"
b0000000100101111 <"
#400000000
0"
b0000000101101110 %
b010 )
b0 *
b0 ,
b010 /
00
b0000000101101110 3
b0000000101101110 6
b0000000100101111 9
b0000000100101111 ;
b0000000101101110 =
b0000000101101110 >
b1111111100010000 ?
b0100101010010001 A
b0000000101101110 B
b1111111100010000 C
b0100101010010001 E
b0000000101101110 G
b0000000100101111 I
b0000000101101110 J
b1111111100010000 K
b0100101010010001 M
b00000000101101110 N
b00000000000000000100101010010001 O
b0000000101101110 R
b010 S
0U
0a
1c
0i
0k
b0000000101101110 l
0o
b0000000101101110 r
0u
1w
b0000000101101110 x
0{
b0000000101101110 !"
0$"
b0000000101101110 '"
0*"
b0000000101101110 -"
00"
b0000000101101110 3"
06"
b0000000101101110 9"
b0 >"
b0000000100101111 ?"
#450000000
1"
10
1U
b0000000101101110 [
1i
1o
1u
b0000000101101110 y
b0000000101101110 z
1{
1$"
1*"
10"
16"
#500000000
0"
0$
b0000000101101110 %
b011 '
b010 (
b000 )
b011 -
b010 .
b000 /
00
02
b0000000101101110 3
b0000000101101110 6
b0000000000000000 7
b0000000101101110 8
b0000000101101110 9
b0000000000000000 :
b0000000101101110 ;
b0000000101101110 =
b0000000101101110 >
b1111111010010010 ?
b0000000000000000 A
b0000000101101110 B
b1111111010010010 C
b0000000000000000 E
b0000000101101110 G
b0000000000000000 H
b0000000101101110 I
b0000000101101110 J
b1111111010010010 K
b0000000000000000 M
b00000000101101110 N
b00000000000000000000000000000000 O
b011 P
b010 Q
b0000000101101110 R
b000 S
0T
0U
b0000000000000000 W
b0000000101101110 X
0c
0i
b0000000101101110 l
0o
b0000000101101110 r
0u
0w
b0000000101101110 x
0{
b0000000101101110 !"
0$"
b0000000101101110 '"
0*"
b0000000101101110 -"
00"
b0000000101101110 3"
06"
b0000000101101110 9"
b0000000101101110 <"
b0000000101101110 ?"
