UNIDADE DE CONTROLE/rom.vhd
--Memória ROM com 16 endereços de 18 bits
library ieee;
use ieee.std_logic_1164.all;
use ieee.numeric_std.all;
entity rom is
    port(   clk: in std_logic;
            endereco : in unsigned(3 downto 0);
            dado: out unsigned(17 downto 0)
    );
end entity;
architecture a_rom of rom is
    type mem is array (0 to 15) of unsigned(17 downto 0);
    constant conteudo_rom : mem := (
        -- caso endereco => conteudo
        0 => "111111111111111111",
        1 => "000000000000000001",
        2 => "000000000000000010",
        3 => "000000000000000011",
        4 => "100000000000000100",
        5 => "000000000010000101",
        6 => "000000000000000110",
        7 => "000000000000000111",
        8 => "000000000000001000",
        9 => "000000000000001001",
        10 =>"000000000000001010",
        -- abaixo: casos omissos => (zero em todos os bits)
        others => (others=>'0')
    );
    begin
    process(clk)
        begin
            if(rising_edge(clk)) then
                dado <= conteudo_rom(to_integer(endereco));
            end if;
    end process;
end architecture;

UNIDADE DE CONTROLE/PC.vhd
library ieee;
use ieee.std_logic_1164.all;
use ieee.numeric_std.all;

entity PC is
    port( clk       :in std_logic;
          wr_en     :in std_logic;
          data_in   :in unsigned(3 downto 0);
          data_out  :out unsigned(3 downto 0)
    );
end entity;

architecture a_PC of PC is
    signal registro: unsigned(3 downto 0);
begin
    process(clk, wr_en)
    begin
        if wr_en='1' then
            if rising_edge(clk) then
                registro<=data_in;
            end if;
        end if;
    end process;

        data_out <= registro;
end architecture;

UNIDADE DE CONTROLE/PCROM.vhd
--Conectando o PC à ROM
library ieee;
use ieee.std_logic_1164.all;
use ieee.numeric_std.all;

entity PCROM is
    port( clk       :in std_logic;
          wr_en     :in std_logic;
          data_in_pc   :in unsigned(3 downto 0);
          data_out_rom  :out unsigned(17 downto 0)
    );
end entity;

architecture a_PCROM of PCROM is


    component PC is
        port(   clk       :in std_logic;
                wr_en     :in std_logic;
                data_in   :in unsigned(3 downto 0);
                data_out  :out unsigned(3 downto 0)
        );
    end component;


    component ROM is
        port(   clk: in std_logic;
                endereco : in unsigned(3 downto 0);
                dado: out unsigned(17 downto 0)
            );
    end component;


    signal registro: unsigned(3 downto 0);
        begin
        PC0: PC port map(clk=>clk, wr_en=>wr_en, data_in =>data_in_pc, data_out=>registro);
        ROM0: ROM port map(clk=>clk, endereco=>registro, dado=>data_out_rom);

end architecture;

UNIDADE DE CONTROLE/PCROM_tb.vhd
library ieee;
use ieee.std_logic_1164.all;
use ieee.numeric_std.all;

entity PCROM_tb is
end;

architecture a_PCROM_tb of PCROM_tb is
    component PCROM
        port(   clk       :in std_logic;
                wr_en     :in std_logic;
                data_in_pc   :in unsigned(3 downto 0);
                data_out_rom  :out unsigned(17 downto 0)
            );
    end component;

    constant period_time: time := 100 ns;
    signal finished: std_logic :='0';
    signal clk, wr_en: std_logic;
    signal data_in_pc: unsigned (3 downto 0);
    signal data_out_rom: unsigned (17 downto 0);

        begin
            uut: PCROM port map(clk=>clk, wr_en=>wr_en, data_in_pc=> data_in_pc, data_out_rom=>data_out_rom);

        sim_time_proc: process
        begin  
            wait for 10 us;
            finished<='1';
            wait;
        end process sim_time_proc;
        
        clk_proc: process
        begin
            while finished/='1' loop
                clk <='0';
                wait for period_time/2;
                clk <='1';
                wait for period_time/2;
            end loop;
            wait;
        end process clk_proc;

        process
        begin  
                wait for 200 ns;
                wr_en<='1';
                data_in_pc <="0000";
                wait for 100 ns;
                data_in_pc <="0001";
                wait for 100 ns;
                data_in_pc <="0010";
                wait for 100 ns;
                data_in_pc <="0011";
                wait for 100 ns;
                data_in_pc <="0100";
                wait for 100 ns;
                data_in_pc <="0101";
                wait for 100 ns;
                data_in_pc <="0110";
                wait for 100 ns;
                data_in_pc <="0111";
                wait for 100 ns;
                data_in_pc <="1000";
                wait for 100 ns;
                data_in_pc <="1001";
                wait for 100 ns;
                data_in_pc <="1010";
                wait for 100 ns;
                data_in_pc <="1011";
                wait for 100 ns;
                data_in_pc <="1100";
                wait for 100 ns;
                data_in_pc <="1101";
                wait for 100 ns;
                data_in_pc <="1110";
                wait for 100 ns;
                data_in_pc <="1111";
                wait;
        end process;
end architecture;

UNIDADE DE CONTROLE/PCROM.vcd
$date
  Tue May  2 14:15:31 2023
$end
$version
  GHDL v0
$end
$timescale
  1 fs
$end
$scope module standard $end
$upscope $end
$scope module std_logic_1164 $end
$upscope $end
$scope module numeric_std $end
$upscope $end
$scope module pcrom_tb $end
$var reg 1 ! finished $end
$var reg 1 " clk $end
$var reg 1 # wr_en $end
$var reg 4 $ data_in_pc[3:0] $end
$var reg 18 % data_out_rom[17:0] $end
$scope module uut $end
$var reg 1 & clk $end
$var reg 1 ' wr_en $end
$var reg 4 ( data_in_pc[3:0] $end
$var reg 18 ) data_out_rom[17:0] $end
$var reg 4 * registro[3:0] $end
$scope module pc0 $end
$var reg 1 + clk $end
$var reg 1 , wr_en $end
$var reg 4 - data_in[3:0] $end
$var reg 4 . data_out[3:0] $end
$var reg 4 / registro[3:0] $end
$upscope $end
$scope module rom0 $end
$var reg 1 0 clk $end
$var reg 4 1 endereco[3:0] $end
$var reg 18 2 dado[17:0] $end
$upscope $end
$upscope $end
$upscope $end
$enddefinitions $end
#0
0!
0"
U#
bUUUU $
bUUUUUUUUUUUUUUUUUU %
0&
U'
bUUUU (
bUUUUUUUUUUUUUUUUUU )
bUUUU *
0+
U,
bUUUU -
bUUUU .
bUUUU /
00
bUUUU 1
bUUUUUUUUUUUUUUUUUU 2
#50000000
1"
b111111111111111111 %
1&
b111111111111111111 )
1+
10
b111111111111111111 2
#100000000
0"
0&
0+
00
#150000000
1"
1&
1+
10
#200000000
0"
1#
b0000 $
0&
1'
b0000 (
0+
1,
b0000 -
00
#250000000
1"
1&
b0000 *
1+
b0000 .
b0000 /
10
b0000 1
#300000000
0"
b0001 $
0&
b0001 (
0+
b0001 -
00
#350000000
1"
1&
b0001 *
1+
b0001 .
b0001 /
10
b0001 1
#400000000
0"
b0010 $
0&
b0010 (
0+
b0010 -
00
#450000000
1"
b000000000000000001 %
1&
b000000000000000001 )
b0010 *
1+
b0010 .
b0010 /
10
b0010 1
b000000000000000001 2
#500000000
0"
b0011 $
0&
b0011 (
0+
b0011 -
00
#550000000
1"
b000000000000000010 %
1&
b000000000000000010 )
b0011 *
1+
b0011 .
b0011 /
10
b0011 1
b000000000000000010 2
#600000000
0"
b0100 $
0&
b0100 (
0+
b0100 -
00
#650000000
1"
b000000000000000011 %
1&
b000000000000000011 )
b0100 *
1+
b0100 .
b0100 /
10
b0100 1
b000000000000000011 2
#700000000
0"
b0101 $
0&
b0101 (
0+
b0101 -
00
#750000000
1"
b100000000000000100 %
1&
b100000000000000100 )
b0101 *
1+
b0101 .
b0101 /
10
b0101 1
b100000000000000100 2
#800000000
0"
b0110 $
0&
b0110 (
0+
b0110 -
00
#850000000
1"
b000000000010000101 %
1&
b000000000010000101 )
b0110 *
1+
b0110 .
b0110 /
10
b0110 1
b000000000010000101 2
#900000000
0"
b0111 $
0&
b0111 (
0+
b0111 -
00
#950000000
1"
b000000000000000110 %
1&
b000000000000000110 )
b0111 *
1+
b0111 .
b0111 /
10
b0111 1
b000000000000000110 2
#1000000000
0"
b1000 $
0&
b1000 (
0+
b1000 -
00
#1050000000
1"
b000000000000000111 %
1&
b000000000000000111 )
b1000 *
1+
b1000 .
b1000 /
10
b1000 1
b000000000000000111 2
#1100000000
0"
b1001 $
0&
b1001 (
0+
b1001 -
00
#1150000000
1"
b000000000000001000 %
1&
b000000000000001000 )
b1001 *
1+
b1001 .
b1001 /
10
b1001 1
b000000000000001000 2
#1200000000
0"
b1010 $
0&
b1010 (
0+
b1010 -
00
#1250000000
1"
b000000000000001001 %
1&
b000000000000001001 )
b1010 *
1+
b1010 .
b1010 /
10
b1010 1
b000000000000001001 2
#1300000000
0"
b1011 $
0&
b1011 (
0+
b1011 -
00
#1350000000
1"
b100000000000001010 %
1&
b100000000000001010 )
b1011 *
1+
b1011 .
b1011 /
10
b1011 1
b100000000000001010 2
#1400000000
0"
b1100 $
0&
b1100 (
0+
b1100 -
00
#1450000000
1"
b000000000000000000 %
1&
b000000000000000000 )
b1100 *
1+
b1100 .
b1100 /
10
b1100 1
b000000000000000000 2
#1500000000
0"
b1101 $
0&
b1101 (
0+
b1101 -
00
#1550000000
1"
1&
b1101 *
1+
b1101 .
b1101 /
10
b1101 1
#1600000000
0"
b1110 $
0&
b1110 (
0+
b1110 -
00
#1650000000
1"
1&
b1110 *
1+
b1110 .
b1110 /
10
b1110 1
#1700000000
0"
b1111 $
0&
b1111 (
0+
b1111 -
00
#1750000000
1"
1&
b1111 *
1+
b1111 .
b1111 /
10
b1111 1
