UNIDADE DE CONTROLE/rom.vhd
--Memória ROM com 16 endereços de 18 bits
library ieee;
use ieee.std_logic_1164.all;
use ieee.numeric_std.all;
entity rom is
    port(   clk: in std_logic;
            endereco : in unsigned(3 downto 0);
            dado: out unsigned(17 downto 0)
    );
end entity;
architecture a_rom of rom is
    type mem is array (0 to 15) of unsigned(17 downto 0);
    constant conteudo_rom : mem := (
        -- caso endereco => conteudo
        0 => "001100000000000001",
        1 => "001100000000000011",
        2 => "000000000000000010",
        3 => "000000000000000011",
        4 => "000000000000000100",
        5 => "000000000000000101",
        6 => "000000000000000110",
        7 => "000000000000000111",
        8 => "000000000000001000",
        9 => "000000000000001001",
        10 =>"000000000000001010",
        -- abaixo: casos omissos => (zero em todos os bits)
        others => (others=>'0')
    );
    begin
    process(clk)
        begin
            if(rising_edge(clk)) then
                dado <= conteudo_rom(to_integer(endereco));
            end if;
    end process;
end architecture;

UNIDADE DE CONTROLE/PC.vhd
library ieee;
use ieee.std_logic_1164.all;
use ieee.numeric_std.all;

entity PC is
    port( clk       :in std_logic;
          wr_en     :in std_logic;
          rst       : in std_logic;
          data_in   :in unsigned(3 downto 0);
          data_out  :out unsigned(3 downto 0)
    );
end entity;

architecture a_PC of PC is
    signal registro: unsigned(3 downto 0);
begin
    process(clk, wr_en, rst)
    begin
        if rst = '1' then
            data_out <="0000";
        
        elsif wr_en='1' then
            if rising_edge(clk) then
                registro<=data_in;
            end if;
        end if;
    end process;
        data_out <=registro;
end architecture;

TOPLVL/PCROM.vhd
--Conectando o PC à ROM
library ieee;
use ieee.std_logic_1164.all;
use ieee.numeric_std.all;

entity PCROM is
    port( clk_pr     :in std_logic;
          wr_en     :in std_logic;
          rst       :in std_logic;
          data_in_pc   :in unsigned(3 downto 0);
          data_out_rom  :out unsigned(17 downto 0);
          data_out_pc : out unsigned(3 downto 0) -- usado para fazer a adição de um endereço
    );
end entity;

architecture a_PCROM of PCROM is


    component PC is
        port(   clk       :in std_logic;
                wr_en     :in std_logic;
                rst        :in std_logic;
                data_in   :in unsigned(3 downto 0);
                data_out  :out unsigned(3 downto 0)
        );
    end component;


    component ROM is
        port(   clk: in std_logic;
                endereco : in unsigned(3 downto 0);
                dado: out unsigned(17 downto 0)
            );
    end component;


    signal registro: unsigned(3 downto 0);
        begin
        PC0: PC port map(clk=>clk_pr, wr_en=>wr_en, rst=>rst, data_in =>data_in_pc, data_out=>registro);
        ROM0: ROM port map(clk=>clk_pr, endereco=>registro, dado=>data_out_rom);
        data_out_pc <= registro;
end architecture;

UNIDADE DE CONTROLE/FFT.vhd
--flip flop t
library ieee;
use ieee.std_logic_1164.all;
use ieee.numeric_std.all;

entity FFT is
    port( clk       :in std_logic;
          rst       :in std_logic;
          data_in   :in std_logic;
          data_out  :out std_logic
    );
end entity;

architecture a_FFT of FFT is
    
    signal saida: std_logic;
        begin
    process(clk, rst)
    begin
		saida <='0';
        if rst='1' then
            saida <='0';
        elsif data_in='1' then
            if rising_edge(clk) then
                saida <= not saida;
            end if;
        end if;
        data_out<=saida;
    end process;
end architecture;

UNIDADE DE CONTROLE/un_controle.vhd
--Unidade de controle
library ieee;
use ieee.std_logic_1164.all;
use ieee.numeric_std.all;

entity un_controle is
    port( instr : in unsigned(17 downto 0);
		  clk : in std_logic;
		  rst : in std_logic;
		  jump_en : out std_logic;
		  update_pc : out std_logic
    );
end entity;

architecture a_un_controle of un_controle is

    component FFT is
        port( clk       :in std_logic;
          rst       :in std_logic;
          data_in   :in std_logic;
          data_out  :out std_logic
		);
    end component;
	
	signal opcode : unsigned (3 downto 0);
	signal state : std_logic;
	signal fft_in: std_logic;

	begin
		FFT0 : FFT port map (clk=> clk, rst=> rst, data_in=> fft_in, data_out=> state);
		fft_in <= '1';
		
		opcode <= instr (17 downto 14) when state = '0' else
				  opcode;
				  
		update_pc <= '1' when state = '1' else
					 '0';
					 
		jump_en <= '1' when opcode = "0011" else
				   '0';

end architecture;

UNIDADE DE CONTROLE/TOPLVL_contr.vhd
--Unidade de controle + PC + ROM
library ieee;
use ieee.std_logic_1164.all;
use ieee.numeric_std.all;

entity TOPLVL_contr is
    port( clk_pc: in std_logic;
		  rst : in std_logic;
		  clk_contrl: in std_logic;
		  rom_out :out unsigned(17 downto 0)
	);
end entity;

architecture a_TOPLVL_contr of TOPLVL_contr is

    component un_controle is
       port( instr : in unsigned(17 downto 0);
		  clk : in std_logic;
		  rst : in std_logic;
		  jump_en : out std_logic;
		  update_pc : out std_logic
    );
    end component;
	
	component PCROM is
       port( clk_pr       :in std_logic;
          wr_en     :in std_logic;
		  rst		:in std_logic;
          data_in_pc   :in unsigned(3 downto 0);
          data_out_rom  :out unsigned(17 downto 0);
		  data_out_pc : out unsigned(3 downto 0)
    );
    end component;
	
	
	
	
	signal opcode : unsigned (17 downto 0);
	signal jump : std_logic;
	signal PC_in, PC_out: unsigned (3 downto 0);
	signal enable : std_logic;
	signal up_pc : std_logic;


	begin
		CONTROLE0 : un_controle port map (instr=> opcode, clk=> clk_contrl, rst=> rst, jump_en=> jump, update_pc=>up_pc);
		PCROM0 : PCROM port map (clk_pr=>clk_pc, wr_en=> enable, rst=>rst, data_in_pc=> PC_in, data_out_rom=> opcode, data_out_pc=>PC_out);
		enable <= '1';
		rom_out <= opcode;

		PC_in <= 	opcode (3 downto 0) when jump = '1' else
					PC_out + "0001";

end architecture;

UNIDADE DE CONTROLE/TOPLVL_contr_tb.vhd
library ieee;
use ieee.std_logic_1164.all;
use ieee.numeric_std.all;

entity TOPLVL_contr_tb is
end;

architecture a_TOPLVL_contr_tb of TOPLVL_contr_tb is
    component TOPLVL_contr
        port( clk_pc: in std_logic;
		  rst : in std_logic;
		  clk_contrl: in std_logic;
		  rom_out :out unsigned(17 downto 0)
		);
    end component;

    constant period_time: time := 100 ns;
    signal finished: std_logic :='0';
    signal clk, rst: std_logic;
    signal rom_out_sig: unsigned (17 downto 0);

        begin
            uut: TOPLVL_contr port map(clk_contrl=> clk, rst=>rst, clk_pc=> clk, rom_out=>rom_out_sig);

        sim_time_proc: process
        begin  
            wait for 10 us;
            finished<='1';
            wait;
        end process sim_time_proc;
        
        clk_proc: process
        begin
            while finished/='1' loop
                clk <='0';
                wait for period_time/2;
                clk <='1';
                wait for period_time/2;
            end loop;
            wait;
        end process clk_proc;

        process
        begin  
            wait for 100 ns;
               rst <='1';
            wait for 200 ns;
                rst <='0';
                wait;
        end process;
end architecture;

UNIDADE DE CONTROLE/teste1.vcd
$date
  Thu May  4 22:56:13 2023
$end
$version
  GHDL v0
$end
$timescale
  1 fs
$end
$scope module standard $end
$upscope $end
$scope module std_logic_1164 $end
$upscope $end
$scope module numeric_std $end
$upscope $end
$scope module toplvl_contr_tb $end
$var reg 1 ! finished $end
$var reg 1 " clk $end
$var reg 1 # rst $end
$var reg 18 $ rom_out_sig[17:0] $end
$scope module uut $end
$var reg 1 % clk_pc $end
$var reg 1 & rst $end
$var reg 1 ' clk_contrl $end
$var reg 18 ( rom_out[17:0] $end
$var reg 18 ) opcode[17:0] $end
$var reg 1 * jump $end
$var reg 4 + pc_in[3:0] $end
$var reg 4 , pc_out[3:0] $end
$var reg 1 - enable $end
$var reg 1 . up_pc $end
$scope module controle0 $end
$var reg 18 / instr[17:0] $end
$var reg 1 0 clk $end
$var reg 1 1 rst $end
$var reg 1 2 jump_en $end
$var reg 1 3 update_pc $end
$var reg 4 4 opcode[3:0] $end
$var reg 1 5 state $end
$var reg 1 6 fft_in $end
$scope module fft0 $end
$var reg 1 7 clk $end
$var reg 1 8 rst $end
$var reg 1 9 data_in $end
$var reg 1 : data_out $end
$var reg 1 ; saida $end
$upscope $end
$upscope $end
$scope module pcrom0 $end
$var reg 1 < clk_pr $end
$var reg 1 = wr_en $end
$var reg 1 > rst $end
$var reg 4 ? data_in_pc[3:0] $end
$var reg 18 @ data_out_rom[17:0] $end
$var reg 4 A data_out_pc[3:0] $end
$var reg 4 B registro[3:0] $end
$scope module pc0 $end
$var reg 1 C clk $end
$var reg 1 D wr_en $end
$var reg 1 E rst $end
$var reg 4 F data_in[3:0] $end
$var reg 4 G data_out[3:0] $end
$var reg 4 H registro[3:0] $end
$upscope $end
$scope module rom0 $end
$var reg 1 I clk $end
$var reg 4 J endereco[3:0] $end
$var reg 18 K dado[17:0] $end
$upscope $end
$upscope $end
$upscope $end
$upscope $end
$enddefinitions $end
#0
0!
0"
U#
bUUUUUUUUUUUUUUUUUU $
0%
U&
0'
bUUUUUUUUUUUUUUUUUU (
bUUUUUUUUUUUUUUUUUU )
0*
bXXXX +
bUUUU ,
1-
0.
bUUUUUUUUUUUUUUUUUU /
00
U1
02
03
bUUUU 4
05
16
07
U8
19
0:
0;
0<
1=
U>
bXXXX ?
bUUUUUUUUUUUUUUUUUU @
bUUUU A
bUUUU B
0C
1D
UE
bXXXX F
bUUUU G
bUUUU H
0I
bUUUU J
bUUUUUUUUUUUUUUUUUU K
#50000000
1"
b001100000000000001 $
1%
1'
b001100000000000001 (
b001100000000000001 )
1*
b0001 +
b001100000000000001 /
10
12
b0011 4
17
1;
1<
b0001 ?
b001100000000000001 @
1C
b0001 F
bUUUU G
bXXXX H
1I
b001100000000000001 K
#100000000
0"
1#
0%
1&
0'
bXXXX ,
1.
00
11
13
15
07
18
1:
0;
0<
1>
bXXXX A
bXXXX B
0C
1E
bXXXX G
0I
bXXXX J
#150000000
1"
1%
1'
0.
10
03
05
17
0:
1<
1C
bXXXX G
1I
#200000000
0"
0%
0'
00
07
0<
0C
bXXXX G
0I
#250000000
1"
1%
1'
10
17
1<
1C
bXXXX G
1I
#300000000
0"
0#
0%
0&
0'
00
01
07
08
0<
0>
0C
0E
0I
#350000000
1"
1%
1'
b000X ,
10
17
1;
1<
b000X A
b000X B
1C
b000X G
b0001 H
1I
b000X J
#400000000
0"
0%
0'
1.
00
13
15
07
1:
0;
0<
0C
0I
#450000000
1"
1%
1'
0.
10
03
05
17
0:
1;
1<
1C
1I
#500000000
0"
0%
0'
1.
00
13
15
07
1:
0;
0<
0C
0I
#550000000
1"
1%
1'
0.
10
03
05
17
0:
1;
1<
1C
1I
#600000000
0"
0%
0'
1.
00
13
15
07
1:
0;
0<
0C
0I
#650000000
1"
1%
1'
0.
10
03
05
17
0:
1;
1<
1C
1I
#700000000
0"
0%
0'
1.
00
13
15
07
1:
0;
0<
0C
0I
#750000000
1"
1%
1'
0.
10
03
05
17
0:
1;
1<
1C
1I
#800000000
0"
0%
0'
1.
00
13
15
07
1:
0;
0<
0C
0I
#850000000
1"
1%
1'
0.
10
03
05
17
0:
1;
1<
1C
1I
#900000000
0"
0%
0'
1.
00
13
15
07
1:
0;
0<
0C
0I
#950000000
1"
1%
1'
0.
10
03
05
17
0:
1;
1<
1C
1I
#1000000000
0"
0%
0'
1.
00
13
15
07
1:
0;
0<
0C
0I
#1050000000
1"
1%
1'
0.
10
03
05
17
0:
1;
1<
1C
1I
#1100000000
0"
0%
0'
1.
00
13
15
07
1:
0;
0<
0C
0I
#1150000000
1"
1%
1'
0.
10
03
05
17
0:
1;
1<
1C
1I
#1200000000
0"
0%
0'
1.
00
13
15
07
1:
0;
0<
0C
0I
#1250000000
1"
1%
1'
0.
10
03
05
17
0:
1;
1<
1C
1I
#1300000000
0"
0%
0'
1.
00
13
15
07
1:
0;
0<
0C
0I
#1350000000
1"
1%
1'
0.
10
03
05
17
0:
1;
1<
1C
1I
#1400000000
0"
0%
0'
1.
00
13
15
07
1:
0;
0<
0C
0I
#1450000000
1"
1%
1'
0.
10
03
05
17
0:
1;
1<
1C
1I
#1500000000
0"
0%
0'
1.
00
13
15
07
1:
0;
0<
0C
0I
#1550000000
1"
1%
1'
0.
10
03
05
17
0:
1;
1<
1C
1I
#1600000000
0"
0%
0'
1.
00
13
15
07
1:
0;
0<
0C
0I
#1650000000
1"
1%
1'
0.
10
03
05
17
0:
1;
1<
1C
1I
#1700000000
0"
0%
0'
1.
00
13
15
07
1:
0;
0<
0C
0I
#1750000000
1"
1%
1'
0.
10
03
05
17
0:
1;
1<
1C
1I
#1800000000
0"
0%
0'
1.
00
13
15
07
1:
0;
0<
0C
0I
#1850000000
1"
1%
1'
0.
10
03
05
17
0:
1;
1<
1C
1I
#1900000000
0"
0%
0'
1.
00
13
15
07
1:
0;
0<
0C
0I
#1950000000
1"
1%
1'
0.
10
03
05
17
0:
1;
1<
1C
1I
#2000000000
0"
0%
0'
1.
00
13
15
07
1:
0;
0<
0C
0I
#2050000000
1"
1%
1'
0.
10
03
05
17
0:
1;
1<
1C
1I
#2100000000
0"
0%
0'
1.
00
13
15
07
1:
0;
0<
0C
0I
#2150000000
1"
1%
1'
0.
10
03
05
17
0:
1;
1<
1C
1I
#2200000000
0"
0%
0'
1.
00
13
15
07
1:
0;
0<
0C
0I
#2250000000
1"
1%
1'
0.
10
03
05
17
0:
1;
1<
1C
1I
#2300000000
0"
0%
0'
1.
00
13
15
07
1:
0;
0<
0C
0I
#2350000000
1"
1%
1'
0.
10
03
05
17
0:
1;
1<
1C
1I
#2400000000
0"
0%
0'
1.
00
13
15
07
1:
0;
0<
0C
0I
#2450000000
1"
1%
1'
0.
10
03
05
17
0:
1;
1<
1C
1I
#2500000000
0"
0%
0'
1.
00
13
15
07
1:
0;
0<
0C
0I
#2550000000
1"
1%
1'
0.
10
03
05
17
0:
1;
1<
1C
1I
#2600000000
0"
0%
0'
1.
00
13
15
07
1:
0;
0<
0C
0I
#2650000000
1"
1%
1'
0.
10
03
05
17
0:
1;
1<
1C
1I
#2700000000
0"
0%
0'
1.
00
13
15
07
1:
0;
0<
0C
0I
#2750000000
1"
1%
1'
0.
10
03
05
17
0:
1;
1<
1C
1I
#2800000000
0"
0%
0'
1.
00
13
15
07
1:
0;
0<
0C
0I
#2850000000
1"
1%
1'
0.
10
03
05
17
0:
1;
1<
1C
1I
#2900000000
0"
0%
0'
1.
00
13
15
07
1:
0;
0<
0C
0I
#2950000000
1"
1%
1'
0.
10
03
05
17
0:
1;
1<
1C
1I
#3000000000
0"
0%
0'
1.
00
13
15
07
1:
0;
0<
0C
0I
#3050000000
1"
1%
1'
0.
10
03
05
17
0:
1;
1<
1C
1I
#3100000000
0"
0%
0'
1.
00
13
15
07
1:
0;
0<
0C
0I
#3150000000
1"
1%
1'
0.
10
03
05
17
0:
1;
1<
1C
1I
#3200000000
0"
0%
0'
1.
00
13
15
07
1:
0;
0<
0C
0I
#3250000000
1"
1%
1'
0.
10
03
05
17
0:
1;
1<
1C
1I
#3300000000
0"
0%
0'
1.
00
13
15
07
1:
0;
0<
0C
0I
#3350000000
1"
1%
1'
0.
10
03
05
17
0:
1;
1<
1C
1I
#3400000000
0"
0%
0'
1.
00
13
15
07
1:
0;
0<
0C
0I
#3450000000
1"
1%
1'
0.
10
03
05
17
0:
1;
1<
1C
1I
#3500000000
0"
0%
0'
1.
00
13
15
07
1:
0;
0<
0C
0I
#3550000000
1"
1%
1'
0.
10
03
05
17
0:
1;
1<
1C
1I
#3600000000
0"
0%
0'
1.
00
13
15
07
1:
0;
0<
0C
0I
#3650000000
1"
1%
1'
0.
10
03
05
17
0:
1;
1<
1C
1I
#3700000000
0"
0%
0'
1.
00
13
15
07
1:
0;
0<
0C
0I
#3750000000
1"
1%
1'
0.
10
03
05
17
0:
1;
1<
1C
1I
#3800000000
0"
0%
0'
1.
00
13
15
07
1:
0;
0<
0C
0I
#3850000000
1"
1%
1'
0.
10
03
05
17
0:
1;
1<
1C
1I
#3900000000
0"
0%
0'
1.
00
13
15
07
1:
0;
0<
0C
0I
#3950000000
1"
1%
1'
0.
10
03
05
17
0:
1;
1<
1C
1I
#4000000000
0"
0%
0'
1.
00
13
15
07
1:
0;
0<
0C
0I
#4050000000
1"
1%
1'
0.
10
03
05
17
0:
1;
1<
1C
1I
#4100000000
0"
0%
0'
1.
00
13
15
07
1:
0;
0<
0C
0I
#4150000000
1"
1%
1'
0.
10
03
05
17
0:
1;
1<
1C
1I
#4200000000
0"
0%
0'
1.
00
13
15
07
1:
0;
0<
0C
0I
#4250000000
1"
1%
1'
0.
10
03
05
17
0:
1;
1<
1C
1I
#4300000000
0"
0%
0'
1.
00
13
15
07
1:
0;
0<
0C
0I
#4350000000
1"
1%
1'
0.
10
03
05
17
0:
1;
1<
1C
1I
#4400000000
0"
0%
0'
1.
00
13
15
07
1:
0;
0<
0C
0I
#4450000000
1"
1%
1'
0.
10
03
05
17
0:
1;
1<
1C
1I
#4500000000
0"
0%
0'
1.
00
13
15
07
1:
0;
0<
0C
0I
#4550000000
1"
1%
1'
0.
10
03
05
17
0:
1;
1<
1C
1I
#4600000000
0"
0%
0'
1.
00
13
15
07
1:
0;
0<
0C
0I
#4650000000
1"
1%
1'
0.
10
03
05
17
0:
1;
1<
1C
1I
#4700000000
0"
0%
0'
1.
00
13
15
07
1:
0;
0<
0C
0I
#4750000000
1"
1%
1'
0.
10
03
05
17
0:
1;
1<
1C
1I
#4800000000
0"
0%
0'
1.
00
13
15
07
1:
0;
0<
0C
0I
#4850000000
1"
1%
1'
0.
10
03
05
17
0:
1;
1<
1C
1I
#4900000000
0"
0%
0'
1.
00
13
15
07
1:
0;
0<
0C
0I
#4950000000
1"
1%
1'
0.
10
03
05
17
0:
1;
1<
1C
1I
#5000000000
0"
0%
0'
1.
00
13
15
07
1:
0;
0<
0C
0I
#5050000000
1"
1%
1'
0.
10
03
05
17
0:
1;
1<
1C
1I
#5100000000
0"
0%
0'
1.
00
13
15
07
1:
0;
0<
0C
0I
#5150000000
1"
1%
1'
0.
10
03
05
17
0:
1;
1<
1C
1I
#5200000000
0"
0%
0'
1.
00
13
15
07
1:
0;
0<
0C
0I
#5250000000
1"
1%
1'
0.
10
03
05
17
0:
1;
1<
1C
1I
#5300000000
0"
0%
0'
1.
00
13
15
07
1:
0;
0<
0C
0I
#5350000000
1"
1%
1'
0.
10
03
05
17
0:
1;
1<
1C
1I
#5400000000
0"
0%
0'
1.
00
13
15
07
1:
0;
0<
0C
0I
#5450000000
1"
1%
1'
0.
10
03
05
17
0:
1;
1<
1C
1I
#5500000000
0"
0%
0'
1.
00
13
15
07
1:
0;
0<
0C
0I
#5550000000
1"
1%
1'
0.
10
03
05
17
0:
1;
1<
1C
1I
#5600000000
0"
0%
0'
1.
00
13
15
07
1:
0;
0<
0C
0I
#5650000000
1"
1%
1'
0.
10
03
05
17
0:
1;
1<
1C
1I
#5700000000
0"
0%
0'
1.
00
13
15
07
1:
0;
0<
0C
0I
#5750000000
1"
1%
1'
0.
10
03
05
17
0:
1;
1<
1C
1I
#5800000000
0"
0%
0'
1.
00
13
15
07
1:
0;
0<
0C
0I
#5850000000
1"
1%
1'
0.
10
03
05
17
0:
1;
1<
1C
1I
#5900000000
0"
0%
0'
1.
00
13
15
07
1:
0;
0<
0C
0I
#5950000000
1"
1%
1'
0.
10
03
05
17
0:
1;
1<
1C
1I
#6000000000
0"
0%
0'
1.
00
13
15
07
1:
0;
0<
0C
0I
#6050000000
1"
1%
1'
0.
10
03
05
17
0:
1;
1<
1C
1I
#6100000000
0"
0%
0'
1.
00
13
15
07
1:
0;
0<
0C
0I
#6150000000
1"
1%
1'
0.
10
03
05
17
0:
1;
1<
1C
1I
#6200000000
0"
0%
0'
1.
00
13
15
07
1:
0;
0<
0C
0I
#6250000000
1"
1%
1'
0.
10
03
05
17
0:
1;
1<
1C
1I
#6300000000
0"
0%
0'
1.
00
13
15
07
1:
0;
0<
0C
0I
#6350000000
1"
1%
1'
0.
10
03
05
17
0:
1;
1<
1C
1I
#6400000000
0"
0%
0'
1.
00
13
15
07
1:
0;
0<
0C
0I
#6450000000
1"
1%
1'
0.
10
03
05
17
0:
1;
1<
1C
1I
#6500000000
0"
0%
0'
1.
00
13
15
07
1:
0;
0<
0C
0I
#6550000000
1"
1%
1'
0.
10
03
05
17
0:
1;
1<
1C
1I
#6600000000
0"
0%
0'
1.
00
13
15
07
1:
0;
0<
0C
0I
#6650000000
1"
1%
1'
0.
10
03
05
17
0:
1;
1<
1C
1I
#6700000000
0"
0%
0'
1.
00
13
15
07
1:
0;
0<
0C
0I
#6750000000
1"
1%
1'
0.
10
03
05
17
0:
1;
1<
1C
1I
#6800000000
0"
0%
0'
1.
00
13
15
07
1:
0;
0<
0C
0I
#6850000000
1"
1%
1'
0.
10
03
05
17
0:
1;
1<
1C
1I
#6900000000
0"
0%
0'
1.
00
13
15
07
1:
0;
0<
0C
0I
#6950000000
1"
1%
1'
0.
10
03
05
17
0:
1;
1<
1C
1I
#7000000000
0"
0%
0'
1.
00
13
15
07
1:
0;
0<
0C
0I
#7050000000
1"
1%
1'
0.
10
03
05
17
0:
1;
1<
1C
1I
#7100000000
0"
0%
0'
1.
00
13
15
07
1:
0;
0<
0C
0I
#7150000000
1"
1%
1'
0.
10
03
05
17
0:
1;
1<
1C
1I
#7200000000
0"
0%
0'
1.
00
13
15
07
1:
0;
0<
0C
0I
#7250000000
1"
1%
1'
0.
10
03
05
17
0:
1;
1<
1C
1I
#7300000000
0"
0%
0'
1.
00
13
15
07
1:
0;
0<
0C
0I
#7350000000
1"
1%
1'
0.
10
03
05
17
0:
1;
1<
1C
1I
#7400000000
0"
0%
0'
1.
00
13
15
07
1:
0;
0<
0C
0I
#7450000000
1"
1%
1'
0.
10
03
05
17
0:
1;
1<
1C
1I
#7500000000
0"
0%
0'
1.
00
13
15
07
1:
0;
0<
0C
0I
#7550000000
1"
1%
1'
0.
10
03
05
17
0:
1;
1<
1C
1I
#7600000000
0"
0%
0'
1.
00
13
15
07
1:
0;
0<
0C
0I
#7650000000
1"
1%
1'
0.
10
03
05
17
0:
1;
1<
1C
1I
#7700000000
0"
0%
0'
1.
00
13
15
07
1:
0;
0<
0C
0I
#7750000000
1"
1%
1'
0.
10
03
05
17
0:
1;
1<
1C
1I
#7800000000
0"
0%
0'
1.
00
13
15
07
1:
0;
0<
0C
0I
#7850000000
1"
1%
1'
0.
10
03
05
17
0:
1;
1<
1C
1I
#7900000000
0"
0%
0'
1.
00
13
15
07
1:
0;
0<
0C
0I
#7950000000
1"
1%
1'
0.
10
03
05
17
0:
1;
1<
1C
1I
#8000000000
0"
0%
0'
1.
00
13
15
07
1:
0;
0<
0C
0I
#8050000000
1"
1%
1'
0.
10
03
05
17
0:
1;
1<
1C
1I
#8100000000
0"
0%
0'
1.
00
13
15
07
1:
0;
0<
0C
0I
#8150000000
1"
1%
1'
0.
10
03
05
17
0:
1;
1<
1C
1I
#8200000000
0"
0%
0'
1.
00
13
15
07
1:
0;
0<
0C
0I
#8250000000
1"
1%
1'
0.
10
03
05
17
0:
1;
1<
1C
1I
#8300000000
0"
0%
0'
1.
00
13
15
07
1:
0;
0<
0C
0I
#8350000000
1"
1%
1'
0.
10
03
05
17
0:
1;
1<
1C
1I
#8400000000
0"
0%
0'
1.
00
13
15
07
1:
0;
0<
0C
0I
#8450000000
1"
1%
1'
0.
10
03
05
17
0:
1;
1<
1C
1I
#8500000000
0"
0%
0'
1.
00
13
15
07
1:
0;
0<
0C
0I
#8550000000
1"
1%
1'
0.
10
03
05
17
0:
1;
1<
1C
1I
#8600000000
0"
0%
0'
1.
00
13
15
07
1:
0;
0<
0C
0I
#8650000000
1"
1%
1'
0.
10
03
05
17
0:
1;
1<
1C
1I
#8700000000
0"
0%
0'
1.
00
13
15
07
1:
0;
0<
0C
0I
#8750000000
1"
1%
1'
0.
10
03
05
17
0:
1;
1<
1C
1I
#8800000000
0"
0%
0'
1.
00
13
15
07
1:
0;
0<
0C
0I
#8850000000
1"
1%
1'
0.
10
03
05
17
0:
1;
1<
1C
1I
#8900000000
0"
0%
0'
1.
00
13
15
07
1:
0;
0<
0C
0I
#8950000000
1"
1%
1'
0.
10
03
05
17
0:
1;
1<
1C
1I
#9000000000
0"
0%
0'
1.
00
13
15
07
1:
0;
0<
0C
0I
#9050000000
1"
1%
1'
0.
10
03
05
17
0:
1;
1<
1C
1I
#9100000000
0"
0%
0'
1.
00
13
15
07
1:
0;
0<
0C
0I
#9150000000
1"
1%
1'
0.
10
03
05
17
0:
1;
1<
1C
1I
#9200000000
0"
0%
0'
1.
00
13
15
07
1:
0;
0<
0C
0I
#9250000000
1"
1%
1'
0.
10
03
05
17
0:
1;
1<
1C
1I
#9300000000
0"
0%
0'
1.
00
13
15
07
1:
0;
0<
0C
0I
#9350000000
1"
1%
1'
0.
10
03
05
17
0:
1;
1<
1C
1I
#9400000000
0"
0%
0'
1.
00
13
15
07
1:
0;
0<
0C
0I
#9450000000
1"
1%
1'
0.
10
03
05
17
0:
1;
1<
1C
1I
#9500000000
0"
0%
0'
1.
00
13
15
07
1:
0;
0<
0C
0I
#9550000000
1"
1%
1'
0.
10
03
05
17
0:
1;
1<
1C
1I
#9600000000
0"
0%
0'
1.
00
13
15
07
1:
0;
0<
0C
0I
#9650000000
1"
1%
1'
0.
10
03
05
17
0:
1;
1<
1C
1I
#9700000000
0"
0%
0'
1.
00
13
15
07
1:
0;
0<
0C
0I
#9750000000
1"
1%
1'
0.
10
03
05
17
0:
1;
1<
1C
1I
#9800000000
0"
0%
0'
1.
00
13
15
07
1:
0;
0<
0C
0I
#9850000000
1"
1%
1'
0.
10
03
05
17
0:
1;
1<
1C
1I
#9900000000
0"
0%
0'
1.
00
13
15
07
1:
0;
0<
0C
0I
#9950000000
1"
1%
1'
0.
10
03
05
17
0:
1;
1<
1C
1I
#10000000000
1!
0"
0%
0'
1.
00
13
15
07
1:
0;
0<
0C
0I
#10050000000
1"
1%
1'
0.
10
03
05
17
0:
1;
1<
1C
1I
