BANCOREG/REGISTRADOR.vhd
library ieee;
use ieee.std_logic_1164.all;
use ieee.numeric_std.all;

entity REGISTRADOR is
    port( clk       :in std_logic;
          rst       :in std_logic;
          wr_en     :in std_logic;
          data_in   :in unsigned(15 downto 0);
          data_out  :out unsigned(15 downto 0)
    );
end entity;

architecture a_REGISTRADOR of REGISTRADOR is
    signal registro: unsigned(15 downto 0);
begin
    process(clk, rst, wr_en)
    begin
        if rst='1' then
            registro <="0000000000000000";
        elsif wr_en='1' then
            if rising_edge(clk) then
                registro<=data_in;
            end if;
        end if;
    end process;

        data_out <= registro;
end architecture;

BANCOREG/BANCOREG.vhd
library ieee;
use ieee.std_logic_1164.all;
use ieee.numeric_std.all;

entity BANCOREG is
    port(
        reg1: in unsigned(2 downto 0);
        reg2: in unsigned(2 downto 0);
        dado: in unsigned(15 downto 0);
        wr_reg: in unsigned(2 downto 0);
        wr_en: in std_logic;
        clk: in std_logic;
        rst: in std_logic;
        read_data1: out unsigned(15 downto 0);
        read_data2: out unsigned(15 downto 0)
    );
end entity;
architecture a_BANCOREG of BANCOREG is
    component REGISTRADOR is
        port(
            clk       :in std_logic;
            rst       :in std_logic;
            wr_en     :in std_logic;
            data_in   :in unsigned(15 downto 0);
            data_out  :out unsigned(15 downto 0)
      );
    end component;

    signal r_data0, r_data1, r_data2, r_data3, r_data4, r_data5, r_data6, r_data7: unsigned(15 downto 0);
    signal wr_en0, wr_en1, wr_en2, wr_en3, wr_en4, wr_en5, wr_en6, wr_en7: std_logic;
        begin
        REGISTRADOR0: REGISTRADOR port map(clk=> clk, rst=>rst, wr_en=>wr_en0, data_in=>dado, data_out=>r_data0);
        REGISTRADOR1: REGISTRADOR port map(clk=> clk, rst=>rst, wr_en=>wr_en1, data_in=>dado, data_out=>r_data1);
        REGISTRADOR2: REGISTRADOR port map(clk=> clk, rst=>rst, wr_en=>wr_en2, data_in=>dado, data_out=>r_data2);
        REGISTRADOR3: REGISTRADOR port map(clk=> clk, rst=>rst, wr_en=>wr_en3, data_in=>dado, data_out=>r_data3);
        REGISTRADOR4: REGISTRADOR port map(clk=> clk, rst=>rst, wr_en=>wr_en4, data_in=>dado, data_out=>r_data4);
        REGISTRADOR5: REGISTRADOR port map(clk=> clk, rst=>rst, wr_en=>wr_en5, data_in=>dado, data_out=>r_data5);
        REGISTRADOR6: REGISTRADOR port map(clk=> clk, rst=>rst, wr_en=>wr_en6, data_in=>dado, data_out=>r_data6);
        REGISTRADOR7: REGISTRADOR port map(clk=> clk, rst=>rst, wr_en=>wr_en7, data_in=>dado, data_out=>r_data7);
        
        read_data1 <= r_data0 when reg1 = "000" else
                      r_data1 when reg1 ="001" else
                      r_data2 when reg1 = "010" else
                      r_data3 when reg1 = "011" else
                      r_data4 when reg1 ="100" else
                      r_data5 when reg1 = "101" else
                      r_data6 when reg1 = "110" else
                      r_data7 when reg1 ="111" else
                      "0000000000000000";

        read_data2 <= r_data0 when reg2 = "000" else
                      r_data1 when reg2 ="001" else
                      r_data2 when reg2 = "010" else
                      r_data3 when reg2 = "011" else
                      r_data4 when reg2 ="100" else
                      r_data5 when reg2 = "101" else
                      r_data6 when reg2 = "110" else
                      r_data7 when reg2 ="111" else
                      "0000000000000000";
        
        wr_en0 <= wr_en when wr_reg ="000" else '0';
        wr_en1 <= wr_en when wr_reg ="001" else '0';
        wr_en2 <= wr_en when wr_reg ="010" else '0';
        wr_en3 <= wr_en when wr_reg ="011" else '0';
        wr_en4 <= wr_en when wr_reg ="100" else '0';
        wr_en5 <= wr_en when wr_reg ="101" else '0';
        wr_en6 <= wr_en when wr_reg ="110" else '0';
        wr_en7 <= wr_en when wr_reg ="111" else '0';

    end architecture;

BANCOREG/BANCOREG_tb.vhd
library ieee;
use ieee.std_logic_1164.all;
use ieee.numeric_std.all;

entity BANCOREG_tb is
end;

architecture a_BANCOREG_tb of BANCOREG_tb is
    component BANCOREG
        port(
            reg1: in unsigned(2 downto 0);
            reg2: in unsigned(2 downto 0);
            dado: in unsigned(15 downto 0);
            wr_reg: in unsigned(2 downto 0);
            wr_en: in std_logic;
            clk: in std_logic;
            rst: in std_logic;
            read_data1: out unsigned(15 downto 0);
            read_data2: out unsigned(15 downto 0)
        );
    end component;
    constant period_time: time := 100 ns;
    signal finished: std_logic :='0';
    signal clk, rst, wr_en: std_logic;
    signal dado, read_data1, read_data2:unsigned (15 downto 0);
    signal reg1, reg2, wr_reg: unsigned  (2 downto 0);

        begin
            uut: BANCOREG port map(clk=>clk, rst=>rst, wr_en=>wr_en, dado=>dado,
             read_data1=>read_data1, read_data2=>read_data2, reg1=>reg1, reg2=>reg2, wr_reg=>wr_reg);

        reset_global: process
        begin
            rst<='1';
            wait for period_time*2;
            rst<='0';
            wait;
        end process;

        sim_time_proc: process
        begin  
            wait for 10 us;
            finished<='1';
            wait;
        end process sim_time_proc;
        
        clk_proc: process
        begin
            while finished/='1' loop
                clk <='0';
                wait for period_time/2;
                clk <='1';
                wait for period_time/2;
            end loop;
            wait;
        end process clk_proc;

        process
        begin  
                wait for 200 ns;
                wr_reg<="001";
                wr_en<='1';
                reg1<="000";
                reg2<="001";
                dado<="1111111111111111";

                wait for 100 ns;
                wr_reg<="000";
                wr_en<='1';
                reg1<="000";
                reg2<="001";
                dado<="1001111111100111";
                

                wait for 100 ns;
                wr_reg<="010";
                wr_en<='1';
                reg1<="101";
                reg2<="111";
                dado<="1001111000000111";
                

                wait for 100 ns;
                wr_reg<="111";
                wr_en<='1';
                reg1<="000";
                reg2<="111";
                dado<="1001100011100111";
                

                wait for 100 ns;
                wr_reg<="000";
                wr_en<='1';
                reg1<="000";
                reg2<="001";
                dado<="1001111111100111";
                wait;
        end process;
end architecture a_BANCOREG_tb;

BANCOREG/BANCOREG.vcd
$date
  Wed Apr 19 12:11:23 2023
$end
$version
  GHDL v0
$end
$timescale
  1 fs
$end
$scope module standard $end
$upscope $end
$scope module std_logic_1164 $end
$upscope $end
$scope module numeric_std $end
$upscope $end
$scope module bancoreg_tb $end
$var reg 1 ! finished $end
$var reg 1 " clk $end
$var reg 1 # rst $end
$var reg 1 $ wr_en $end
$var reg 16 % dado[15:0] $end
$var reg 16 & read_data1[15:0] $end
$var reg 16 ' read_data2[15:0] $end
$var reg 3 ( reg1[2:0] $end
$var reg 3 ) reg2[2:0] $end
$var reg 3 * wr_reg[2:0] $end
$scope module uut $end
$var reg 3 + reg1[2:0] $end
$var reg 3 , reg2[2:0] $end
$var reg 16 - dado[15:0] $end
$var reg 3 . wr_reg[2:0] $end
$var reg 1 / wr_en $end
$var reg 1 0 clk $end
$var reg 1 1 rst $end
$var reg 16 2 read_data1[15:0] $end
$var reg 16 3 read_data2[15:0] $end
$var reg 16 4 r_data0[15:0] $end
$var reg 16 5 r_data1[15:0] $end
$var reg 16 6 r_data2[15:0] $end
$var reg 16 7 r_data3[15:0] $end
$var reg 16 8 r_data4[15:0] $end
$var reg 16 9 r_data5[15:0] $end
$var reg 16 : r_data6[15:0] $end
$var reg 16 ; r_data7[15:0] $end
$var reg 1 < wr_en0 $end
$var reg 1 = wr_en1 $end
$var reg 1 > wr_en2 $end
$var reg 1 ? wr_en3 $end
$var reg 1 @ wr_en4 $end
$var reg 1 A wr_en5 $end
$var reg 1 B wr_en6 $end
$var reg 1 C wr_en7 $end
$scope module registrador0 $end
$var reg 1 D clk $end
$var reg 1 E rst $end
$var reg 1 F wr_en $end
$var reg 16 G data_in[15:0] $end
$var reg 16 H data_out[15:0] $end
$var reg 16 I registro[15:0] $end
$upscope $end
$scope module registrador1 $end
$var reg 1 J clk $end
$var reg 1 K rst $end
$var reg 1 L wr_en $end
$var reg 16 M data_in[15:0] $end
$var reg 16 N data_out[15:0] $end
$var reg 16 O registro[15:0] $end
$upscope $end
$scope module registrador2 $end
$var reg 1 P clk $end
$var reg 1 Q rst $end
$var reg 1 R wr_en $end
$var reg 16 S data_in[15:0] $end
$var reg 16 T data_out[15:0] $end
$var reg 16 U registro[15:0] $end
$upscope $end
$scope module registrador3 $end
$var reg 1 V clk $end
$var reg 1 W rst $end
$var reg 1 X wr_en $end
$var reg 16 Y data_in[15:0] $end
$var reg 16 Z data_out[15:0] $end
$var reg 16 [ registro[15:0] $end
$upscope $end
$scope module registrador4 $end
$var reg 1 \ clk $end
$var reg 1 ] rst $end
$var reg 1 ^ wr_en $end
$var reg 16 _ data_in[15:0] $end
$var reg 16 ` data_out[15:0] $end
$var reg 16 a registro[15:0] $end
$upscope $end
$scope module registrador5 $end
$var reg 1 b clk $end
$var reg 1 c rst $end
$var reg 1 d wr_en $end
$var reg 16 e data_in[15:0] $end
$var reg 16 f data_out[15:0] $end
$var reg 16 g registro[15:0] $end
$upscope $end
$scope module registrador6 $end
$var reg 1 h clk $end
$var reg 1 i rst $end
$var reg 1 j wr_en $end
$var reg 16 k data_in[15:0] $end
$var reg 16 l data_out[15:0] $end
$var reg 16 m registro[15:0] $end
$upscope $end
$scope module registrador7 $end
$var reg 1 n clk $end
$var reg 1 o rst $end
$var reg 1 p wr_en $end
$var reg 16 q data_in[15:0] $end
$var reg 16 r data_out[15:0] $end
$var reg 16 s registro[15:0] $end
$upscope $end
$upscope $end
$upscope $end
$enddefinitions $end
#0
0!
0"
1#
U$
bUUUUUUUUUUUUUUUU %
b0000000000000000 &
b0000000000000000 '
bUUU (
bUUU )
bUUU *
bUUU +
bUUU ,
bUUUUUUUUUUUUUUUU -
bUUU .
U/
00
11
b0000000000000000 2
b0000000000000000 3
b0000000000000000 4
b0000000000000000 5
b0000000000000000 6
b0000000000000000 7
b0000000000000000 8
b0000000000000000 9
b0000000000000000 :
b0000000000000000 ;
0<
0=
0>
0?
0@
0A
0B
0C
0D
1E
0F
bUUUUUUUUUUUUUUUU G
b0000000000000000 H
b0000000000000000 I
0J
1K
0L
bUUUUUUUUUUUUUUUU M
b0000000000000000 N
b0000000000000000 O
0P
1Q
0R
bUUUUUUUUUUUUUUUU S
b0000000000000000 T
b0000000000000000 U
0V
1W
0X
bUUUUUUUUUUUUUUUU Y
b0000000000000000 Z
b0000000000000000 [
0\
1]
0^
bUUUUUUUUUUUUUUUU _
b0000000000000000 `
b0000000000000000 a
0b
1c
0d
bUUUUUUUUUUUUUUUU e
b0000000000000000 f
b0000000000000000 g
0h
1i
0j
bUUUUUUUUUUUUUUUU k
b0000000000000000 l
b0000000000000000 m
0n
1o
0p
bUUUUUUUUUUUUUUUU q
b0000000000000000 r
b0000000000000000 s
#50000000
1"
10
1D
1J
1P
1V
1\
1b
1h
1n
#100000000
0"
00
0D
0J
0P
0V
0\
0b
0h
0n
#150000000
1"
10
1D
1J
1P
1V
1\
1b
1h
1n
#200000000
0"
0#
1$
b1111111111111111 %
b000 (
b001 )
b001 *
b000 +
b001 ,
b1111111111111111 -
b001 .
1/
00
01
1=
0D
0E
b1111111111111111 G
0J
0K
1L
b1111111111111111 M
0P
0Q
b1111111111111111 S
0V
0W
b1111111111111111 Y
0\
0]
b1111111111111111 _
0b
0c
b1111111111111111 e
0h
0i
b1111111111111111 k
0n
0o
b1111111111111111 q
#250000000
1"
b1111111111111111 '
10
b1111111111111111 3
b1111111111111111 5
1D
1J
b1111111111111111 N
b1111111111111111 O
1P
1V
1\
1b
1h
1n
#300000000
0"
b1001111111100111 %
b000 *
b1001111111100111 -
b000 .
00
1<
0=
0D
1F
b1001111111100111 G
0J
0L
b1001111111100111 M
0P
b1001111111100111 S
0V
b1001111111100111 Y
0\
b1001111111100111 _
0b
b1001111111100111 e
0h
b1001111111100111 k
0n
b1001111111100111 q
#350000000
1"
b1001111111100111 &
10
b1001111111100111 2
b1001111111100111 4
1D
b1001111111100111 H
b1001111111100111 I
1J
1P
1V
1\
1b
1h
1n
#400000000
0"
b1001111000000111 %
b0000000000000000 &
b0000000000000000 '
b101 (
b111 )
b010 *
b101 +
b111 ,
b1001111000000111 -
b010 .
00
b0000000000000000 2
b0000000000000000 3
0<
1>
0D
0F
b1001111000000111 G
0J
b1001111000000111 M
0P
1R
b1001111000000111 S
0V
b1001111000000111 Y
0\
b1001111000000111 _
0b
b1001111000000111 e
0h
b1001111000000111 k
0n
b1001111000000111 q
#450000000
1"
10
b1001111000000111 6
1D
1J
1P
b1001111000000111 T
b1001111000000111 U
1V
1\
1b
1h
1n
#500000000
0"
b1001100011100111 %
b1001111111100111 &
b000 (
b111 *
b000 +
b1001100011100111 -
b111 .
00
b1001111111100111 2
0>
1C
0D
b1001100011100111 G
0J
b1001100011100111 M
0P
0R
b1001100011100111 S
0V
b1001100011100111 Y
0\
b1001100011100111 _
0b
b1001100011100111 e
0h
b1001100011100111 k
0n
1p
b1001100011100111 q
#550000000
1"
b1001100011100111 '
10
b1001100011100111 3
b1001100011100111 ;
1D
1J
1P
1V
1\
1b
1h
1n
b1001100011100111 r
b1001100011100111 s
#600000000
0"
b1001111111100111 %
b1111111111111111 '
b001 )
b000 *
b001 ,
b1001111111100111 -
b000 .
00
b1111111111111111 3
1<
0C
0D
1F
b1001111111100111 G
0J
b1001111111100111 M
0P
b1001111111100111 S
0V
b1001111111100111 Y
0\
b1001111111100111 _
0b
b1001111111100111 e
0h
b1001111111100111 k
0n
0p
b1001111111100111 q
